Hello33423310/__init__.py
Hello33423310/hello.py
Hello33423310-0.1.dist-info/LICENSE
Hello33423310-0.1.dist-info/METADATA
Hello33423310-0.1.dist-info/WHEEL
Hello33423310-0.1.dist-info/top_level.txt
Hello33423310-0.1.dist-info/RECORD
