Metadata-Version: 2.1
Name: Hello33423310
Version: 0.1
Summary: Deskripsi untuk kode program
Home-page: https://github.com/syahrulcaem/Informasi_negara
Author: hanifaslamm
Author-email: <aslamhanif141@gmail.com>
License: MIT
Keywords: Hello
Platform: UNKNOWN
Classifier: Development Status :: 1 - Planning
License-File: LICENSE
